fds/__init__.py
fds/sdk/__init__.py
fds/sdk/StocksAPIforDigitalPortals/__init__.py
fds/sdk/StocksAPIforDigitalPortals/api_client.py
fds/sdk/StocksAPIforDigitalPortals/configuration.py
fds/sdk/StocksAPIforDigitalPortals/exceptions.py
fds/sdk/StocksAPIforDigitalPortals/model_utils.py
fds/sdk/StocksAPIforDigitalPortals/rest.py
fds/sdk/StocksAPIforDigitalPortals/api/__init__.py
fds/sdk/StocksAPIforDigitalPortals/api/company_api.py
fds/sdk/StocksAPIforDigitalPortals/api/stock_api.py
fds/sdk/StocksAPIforDigitalPortals/apis/__init__.py
fds/sdk/StocksAPIforDigitalPortals/model/__init__.py
fds/sdk/StocksAPIforDigitalPortals/model/attributes_member.py
fds/sdk/StocksAPIforDigitalPortals/model/cursor_based_pagination_output_object.py
fds/sdk/StocksAPIforDigitalPortals/model/cursor_based_pagination_output_object_without_total.py
fds/sdk/StocksAPIforDigitalPortals/model/error_meta_object.py
fds/sdk/StocksAPIforDigitalPortals/model/error_object.py
fds/sdk/StocksAPIforDigitalPortals/model/inline_response200.py
fds/sdk/StocksAPIforDigitalPortals/model/inline_response2001.py
fds/sdk/StocksAPIforDigitalPortals/model/inline_response20010.py
fds/sdk/StocksAPIforDigitalPortals/model/inline_response20010_data.py
fds/sdk/StocksAPIforDigitalPortals/model/inline_response20010_data_currency.py
fds/sdk/StocksAPIforDigitalPortals/model/inline_response20010_data_dates.py
fds/sdk/StocksAPIforDigitalPortals/model/inline_response20010_data_dividends.py
fds/sdk/StocksAPIforDigitalPortals/model/inline_response20010_data_gross.py
fds/sdk/StocksAPIforDigitalPortals/model/inline_response20010_data_occurrence.py
fds/sdk/StocksAPIforDigitalPortals/model/inline_response20010_data_occurrence_frequency.py
fds/sdk/StocksAPIforDigitalPortals/model/inline_response20010_data_type.py
fds/sdk/StocksAPIforDigitalPortals/model/inline_response20011.py
fds/sdk/StocksAPIforDigitalPortals/model/inline_response20011_data.py
fds/sdk/StocksAPIforDigitalPortals/model/inline_response20012.py
fds.sdk.StocksAPIforDigitalPortals-0.10.21.dist-info/LICENSE
fds.sdk.StocksAPIforDigitalPortals-0.10.21.dist-info/METADATA
fds.sdk.StocksAPIforDigitalPortals-0.10.21.dist-info/WHEEL
fds.sdk.StocksAPIforDigitalPortals-0.10.21.dist-info/top_level.txt
fds.sdk.StocksAPIforDigitalPortals-0.10.21.dist-info/RECORD
